base/__init__.py
base/logger.py
program/__init__.py
program/__version__.py
program/main.py
mypackage_test_001-0.1.1.dist-info/LICENSE
mypackage_test_001-0.1.1.dist-info/METADATA
mypackage_test_001-0.1.1.dist-info/WHEEL
mypackage_test_001-0.1.1.dist-info/top_level.txt
mypackage_test_001-0.1.1.dist-info/RECORD
