Metadata-Version: 2.1
Name: mypackage-test-001
Version: 0.1.1
Summary: My short description for my project.
Home-page: https://github.com/me/null
Author: bing.feng
Author-email: bing.feng@example.com
License: MIT
Classifier: License :: OSI Approved :: MIT License
Classifier: Programming Language :: Python
Classifier: Programming Language :: Python :: 3
Classifier: Programming Language :: Python :: 3.6
Classifier: Programming Language :: Python :: Implementation :: CPython
Classifier: Programming Language :: Python :: Implementation :: PyPy
Requires-Python: >=3.6.0
License-File: LICENSE
